testgen/__init__.py
testgen/__main__.py
testgen/settings.py
testgen/commands/__init__.py
testgen/commands/run_generate_tests.py
testgen/commands/run_get_entities.py
testgen/commands/run_launch_db_config.py
testgen/commands/run_observability_exporter.py
testgen/commands/run_pairwise_contingency_check.py
testgen/commands/run_profiling.py
testgen/commands/run_quick_start.py
testgen/commands/run_refresh_data_chars.py
testgen/commands/run_refresh_score_cards_results.py
testgen/commands/run_rollup_scores.py
testgen/commands/run_test_execution.py
testgen/commands/run_test_metadata_exporter.py
testgen/commands/run_test_validation.py
testgen/commands/run_upgrade_db_config.py
testgen/commands/queries/__init__.py
testgen/commands/queries/contingency_query.py
testgen/commands/queries/execute_tests_query.py
testgen/commands/queries/generate_tests_query.py
testgen/commands/queries/profiling_query.py
testgen/commands/queries/refresh_data_chars_query.py
testgen/commands/queries/rollup_scores_query.py
testgen/common/__init__.py
testgen/common/clean_sql.py
testgen/common/credentials.py
testgen/common/date_service.py
testgen/common/display_service.py
testgen/common/docker_service.py
testgen/common/encrypt.py
testgen/common/get_pipeline_parms.py
testgen/common/logs.py
testgen/common/mixpanel_service.py
testgen/common/process_service.py
testgen/common/read_file.py
testgen/common/read_yaml_metadata_records.py
testgen/common/version_service.py
testgen/common/database/__init__.py
testgen/common/database/database_service.py
testgen/common/database/flavor/__init__.py
testgen/common/database/flavor/bigquery_flavor_service.py
testgen/common/database/flavor/databricks_flavor_service.py
testgen/common/database/flavor/flavor_service.py
testgen/common/database/flavor/mssql_flavor_service.py
testgen/common/database/flavor/postgresql_flavor_service.py
testgen/common/database/flavor/redshift_flavor_service.py
testgen/common/database/flavor/redshift_spectrum_flavor_service.py
dataops_testgen-4.39.2.dist-info/LICENSE
dataops_testgen-4.39.2.dist-info/METADATA
dataops_testgen-4.39.2.dist-info/NOTICE
dataops_testgen-4.39.2.dist-info/WHEEL
dataops_testgen-4.39.2.dist-info/entry_points.txt
dataops_testgen-4.39.2.dist-info/top_level.txt
dataops_testgen-4.39.2.dist-info/RECORD
