Metadata-Version: 2.1
Name: dataops-testgen
Version: 4.39.2
Summary: DataKitchen's Data Quality DataOps TestGen
Author-email: "DataKitchen, Inc." <info@datakitchen.io>
Maintainer-email: "DataKitchen, Inc." <info@datakitchen.io>
Project-URL: Source Code, https://github.com/DataKitchen/dataops-testgen
Project-URL: Bug Tracker, https://github.com/DataKitchen/dataops-testgen/issues
Project-URL: Documentation, https://docs.datakitchen.io/articles/#!dataops-testgen-help/dataops-testgen-help
Project-URL: Release Notes, https://docs.datakitchen.io/articles/#!dataops-testgen-help/testgen-release-notes
Project-URL: Slack, https://data-observability-slack.datakitchen.io/join
Project-URL: Homepage, https://example.com
Keywords: dataops,data,quality,testing,database,profiling
Classifier: License :: OSI Approved :: Apache Software License
Classifier: Development Status :: 5 - Production/Stable
Classifier: Operating System :: OS Independent
Classifier: Programming Language :: Python :: 3.12
Classifier: Topic :: System :: Monitoring
Requires-Python: >=3.12
License-File: LICENSE
License-File: NOTICE
Requires-Dist: PyYAML ==6.0.1
Requires-Dist: click ==8.1.3
Requires-Dist: sqlalchemy ==1.4.46
Requires-Dist: databricks-sql-connector ==2.9.3
Requires-Dist: snowflake-sqlalchemy ==1.6.1
Requires-Dist: sqlalchemy-bigquery ==1.14.1
Requires-Dist: pyodbc ==5.0.0
Requires-Dist: psycopg2-binary ==2.9.9
Requires-Dist: pycryptodome ==3.21
Requires-Dist: prettytable ==3.7.0
Requires-Dist: requests-extensions ==1.1.3
Requires-Dist: numpy ==1.26.4
Requires-Dist: pandas ==2.1.4
Requires-Dist: streamlit ==1.46.1
Requires-Dist: streamlit-extras ==0.3.0
Requires-Dist: streamlit-aggrid ==0.3.4.post3
Requires-Dist: plotly-express ==0.4.1
Requires-Dist: streamlit-authenticator ==0.2.3
Requires-Dist: streamlit-javascript ==0.1.5
Requires-Dist: progress ==1.6
Requires-Dist: beautifulsoup4 ==4.12.3
Requires-Dist: trino ==0.327.0
Requires-Dist: xlsxwriter ==3.2.0
Requires-Dist: psutil ==5.9.8
Requires-Dist: concurrent-log-handler ==0.9.25
Requires-Dist: cryptography ==44.0.1
Requires-Dist: validators ==0.33.0
Requires-Dist: reportlab ==4.2.2
Requires-Dist: pydantic ==1.10.13
Requires-Dist: streamlit-pydantic ==0.6.0
Requires-Dist: cron-converter ==1.2.1
Requires-Dist: cron-descriptor ==2.0.5
Requires-Dist: pybars3 ==0.9.7
Requires-Dist: azure-identity ==1.25.1
Requires-Dist: pyarrow ==18.1.0
Requires-Dist: matplotlib ==3.9.2
Requires-Dist: scipy ==1.14.1
Requires-Dist: jinja2 ==3.1.6
Provides-Extra: dev
Requires-Dist: invoke ==2.2.0 ; extra == 'dev'
Requires-Dist: ruff ==0.4.1 ; extra == 'dev'
Requires-Dist: mypy ==1.9.0 ; extra == 'dev'
Requires-Dist: pre-commit ==3.6.2 ; extra == 'dev'
Requires-Dist: types-PyYAML ==6.0.12.20240311 ; extra == 'dev'
Requires-Dist: types-setuptools ==69.2.0.20240317 ; extra == 'dev'
Requires-Dist: semver ==3.0.2 ; extra == 'dev'
Requires-Dist: pytest ==8.1.1 ; extra == 'dev'
Requires-Dist: pytest-cov ==4.1.0 ; extra == 'dev'
Requires-Dist: tomli ==2.0.1 ; extra == 'dev'
Provides-Extra: release
Requires-Dist: build ==1.2.1 ; extra == 'release'
Requires-Dist: bumpver ==2023.1129 ; extra == 'release'
Requires-Dist: twine ==5.1.1 ; extra == 'release'
